{
    "tables": [
        {
            "model_name": "User",
            "table_name": "users",
            "attributes": [
                {
                    "name": "first_name",
                    "type": "string",
                    "nullable": false,
                    "unique": false
                },
                {
                    "name": "middle_name",
                    "type": "string",
                    "nullable": false,
                    "unique": false
                },
                {
                    "name": "last_name",
                    "type": "integer",
                    "nullable": false,
                    "unique": false
                },
                {
                    "name": "phone_number",
                    "type": "string",
                    "nullable": false,
                    "unique": false
                },
                {
                    "name": "email",
                    "type": "string",
                    "nullable": false,
                    "unique": false
                },
                {
                    "name": "birth_date",
                    "type": "date",
                    "nullable": false,
                    "unique": false
                },
                {
                    "name": "gender",
                    "type": "string",
                    "nullable": false,
                    "unique": false
                },
                {
                    "name": "blood_group",
                    "type": "string",
                    "nullable": false,
                    "unique": false
                },
                {
                    "name": "is_blocked",
                    "type": "boolean",
                    "nullable": false,
                    "unique": false
                },
                {
                    "name": "tags",
                    "type": "text",
                    "nullable": false,
                    "unique": false
                },
                {
                    "name": "image",
                    "type": "file",
                    "nullable": false,
                    "unique": false
                },
                {
                    "name": "is_archived",
                    "type": "boolean",
                    "nullable": false,
                    "unique": false
                }
            ],
            "relations": {
                "hasMany": [
                    {
                        "type": "hasMany",
                        "model_name": "PhoneNumber"
                    }
                ]
            }
        },
        {
            "model_name": "Customer",
            "table_name": "customers",
            "attributes": [
                {
                    "name": "mother_full_name",
                    "type": "string",
                    "nullable": false,
                    "unique": false
                },
                {
                    "name": "medical_condition",
                    "type": "text",
                    "nullable": false,
                    "unique": false
                },
                {
                    "name": "user_id",
                    "type": "foreign_key",
                    "nullable": false,
                    "unique": false
                }
            ],
            "relations": {
                "belongsTo": [
                    {
                        "type": "belongsTo",
                        "model_name": "User",
                        "key": "user_id"
                    }
                ],
                "hasMany": [
                    {
                        "type": "hasMany",
                        "model_name": "PatientProfile"
                    },
                    {
                        "type": "hasMany",
                        "model_name": "Appointment"
                    },
                    {
                        "type": "hasMany",
                        "model_name": "Address"
                    }
                ]
            }
        },
        {
            "model_name": "Clinic",
            "table_name": "clinics",
            "attributes": [
                {
                    "name": "name",
                    "type": "string",
                    "nullable": false,
                    "unique": false
                },
                {
                    "name": "appointment_cost",
                    "type": "float",
                    "nullable": false,
                    "unique": false
                },
                {
                    "name": "user_id",
                    "type": "foreign_key",
                    "nullable": false,
                    "unique": false
                },
                {
                    "name": "working_start_year",
                    "type": "date",
                    "nullable": false,
                    "unique": false
                },
                {
                    "name": "max_appointments",
                    "type": "integer",
                    "nullable": false,
                    "unique": false
                },
                {
                    "name": "appointment_day_range",
                    "type": "integer",
                    "nullable": false,
                    "unique": false
                },
                {
                    "name": "about_us",
                    "type": "string",
                    "nullable": false,
                    "unique": false
                },
                {
                    "name": "experience",
                    "type": "string",
                    "nullable": false,
                    "unique": false
                },
                {
                    "name": "work_gallery",
                    "type": "file",
                    "nullable": false,
                    "unique": false
                }
            ],
            "relations": {
                "belongsTo": [
                    {
                        "type": "belongsTo",
                        "model_name": "User",
                        "key": "user_id"
                    }
                ],
                "hasMany": [
                    {
                        "type": "hasMany",
                        "model_name": "Department"
                    },
                    {
                        "type": "hasMany",
                        "model_name": "Offer"
                    },
                    {
                        "type": "hasMany",
                        "model_name": "Transaction"
                    },
                    {
                        "type": "hasMany",
                        "model_name": "Appointment"
                    },
                    {
                        "type": "hasMany",
                        "model_name": "PatientProfile"
                    },
                    {
                        "type": "hasMany",
                        "model_name": "Prescription"
                    },
                    {
                        "type": "hasMany",
                        "model_name": "Service"
                    },
                    {
                        "type": "hasMany",
                        "model_name": "Schedule"
                    },
                    {
                        "type": "hasMany",
                        "model_name": "ClinicHoliday"
                    }
                ],
                "manyToMany": [
                    {
                        "type": "manyToMany",
                        "model_name": "Specialty"
                    },
                    {
                        "type": "manyToMany",
                        "model_name": "Subscription"
                    }
                ],
                "hasOne": [
                    {
                        "type": "hasOne",
                        "model_name": "Address"
                    }
                ]
            }
        },
        {
            "model_name": "Schedule",
            "table_name": "schedules",
            "attributes": [
                {
                    "name": "clinic_id",
                    "type": "foreign_key",
                    "nullable": false,
                    "unique": false
                },
                {
                    "name": "day_of_week",
                    "type": "string",
                    "nullable": false,
                    "unique": false
                },
                {
                    "name": "start_time",
                    "type": "time",
                    "nullable": false,
                    "unique": false
                },
                {
                    "name": "end_time",
                    "type": "time",
                    "nullable": false,
                    "unique": false
                },
                {
                    "name": "hospital_id",
                    "type": "foreign_key",
                    "nullable": false,
                    "unique": false
                }
            ],
            "relations": {
                "belongsTo": [
                    {
                        "type": "belongsTo",
                        "model_name": "Clinic",
                        "key": "clinic_id"
                    },
                    {
                        "type": "belongsTo",
                        "model_name": "Hospital",
                        "key": "hospital_id"
                    }
                ]
            }
        },
        {
            "model_name": "Hospital",
            "table_name": "hospitals",
            "attributes": [
                {
                    "name": "name",
                    "type": "translatable",
                    "nullable": false,
                    "unique": false
                },
                {
                    "name": "phone_numbers",
                    "type": "json",
                    "nullable": false,
                    "unique": false
                },
                {
                    "name": "images",
                    "type": "file",
                    "nullable": false,
                    "unique": false
                }
            ],
            "relations": {
                "hasOne": [
                    {
                        "type": "hasOne",
                        "model_name": "Address"
                    }
                ],
                "hasMany": [
                    {
                        "type": "hasMany",
                        "model_name": "PhoneNumber"
                    }
                ],
                "manyToMany": [
                    {
                        "type": "hasMany",
                        "model_name": "AvailableDepartment"
                    }
                ]
            }
        },
        {
            "model_name": "PhoneNumber",
            "table_name": "phone_numbers",
            "attributes": [
                {
                    "name": "phone",
                    "type": "string",
                    "nullable": false,
                    "unique": false
                },
                {
                    "name": "user_id",
                    "type": "foreign_key",
                    "nullable": false,
                    "unique": false
                },
                {
                    "name": "hospital_id",
                    "type": "foreign_key",
                    "nullable": false,
                    "unique": false
                }
            ],
            "relations": {
                "belongsTo": [
                    {
                        "type": "belongsTo",
                        "model_name": "User",
                        "key": "user_id"
                    },
                    {
                        "type": "belongsTo",
                        "model_name": "Hospital",
                        "key": "hospital_id"
                    }
                ]
            }
        },
        {
            "model_name": "AvailableDepartment",
            "table_name": "available_departments",
            "attributes": [
                {
                    "name": "name",
                    "type": "translatable",
                    "nullable": false,
                    "unique": false
                },
                {
                    "name": "description",
                    "type": "translatable",
                    "nullable": false,
                    "unique": false
                },
                {
                    "name": "hospital_id",
                    "type": "foreign_key",
                    "nullable": false,
                    "unique": false
                }
            ],
            "relations": {
                "belongsTo": [
                    {
                        "type": "belongsTo",
                        "model_name": "Hospital",
                        "key": "hospital_id"
                    }
                ]
            }
        },
        {
            "model_name": "Speciality",
            "table_name": "specialities",
            "attributes": [
                {
                    "name": "name",
                    "type": "string",
                    "nullable": false,
                    "unique": true
                },
                {
                    "name": "description",
                    "type": "text",
                    "nullable": true,
                    "unique": false
                },
                {
                    "name": "tags",
                    "type": "text",
                    "nullable": true,
                    "unique": false
                }
            ],
            "relations": {
                "manyToMany": [
                    {
                        "type": "manyToMany",
                        "model_name": "Clinic"
                    }
                ]
            }
        },
        {
            "model_name": "Address",
            "table_name": "addresses",
            "attributes": [
                {
                    "name": "name",
                    "type": "string",
                    "nullable": false,
                    "unique": false
                },
                {
                    "name": "city",
                    "type": "string",
                    "nullable": false,
                    "unique": false
                },
                {
                    "name": "lat",
                    "type": "text",
                    "nullable": true,
                    "unique": false
                },
                {
                    "name": "lng",
                    "type": "text",
                    "nullable": true,
                    "unique": false
                },
                {
                    "name": "country",
                    "type": "string",
                    "nullable": false,
                    "unique": false
                },
                {
                    "name": "addressable_id",
                    "type": "unsignedBigInteger",
                    "nullable": false,
                    "unique": false
                },
                {
                    "name": "addressable_type",
                    "type": "string",
                    "nullable": false,
                    "unique": false
                }
            ],
            "relations": []
        },
        {
            "model_name": "City",
            "table_name": "cities",
            "attributes": [
                {
                    "name": "name",
                    "type": "translatable",
                    "nullable": true,
                    "unique": false
                }
            ],
            "relations": {
                "hasMany": [
                    {
                        "type": "hasMany",
                        "model_name": "Address"
                    }
                ]
            }
        },
        {
            "model_name": "ClinicHoliday",
            "table_name": "clinic_holidays",
            "attributes": [
                {
                    "name": "clinic_id",
                    "type": "key",
                    "nullable": false,
                    "unique": false
                },
                {
                    "name": "start_date",
                    "type": "dateTime",
                    "nullable": false,
                    "unique": false
                },
                {
                    "name": "end_date",
                    "type": "dateTime",
                    "nullable": false,
                    "unique": false
                },
                {
                    "name": "reason",
                    "type": "translatable",
                    "nullable": false,
                    "unique": false
                }
            ],
            "relations": {
                "belongsTo": [
                    {
                        "type": "belongsTo",
                        "model_name": "Clinic",
                        "key": "clinic_id"
                    }
                ]
            }
        },
        {
            "model_name": "ServiceCategory",
            "table_name": "service_categories",
            "attributes": [
                {
                    "name": "name",
                    "type": "translatable",
                    "nullable": false,
                    "unique": false
                }
            ],
            "relations": {
                "hasMany": [
                    {
                        "type": "hasMany",
                        "model_name": "Service"
                    }
                ]
            }
        },
        {
            "model_name": "Service",
            "table_name": "services",
            "attributes": [
                {
                    "name": "name",
                    "type": "translatable",
                    "nullable": false,
                    "unique": false
                },
                {
                    "name": "approximate_duration",
                    "type": "integer",
                    "nullable": false,
                    "unique": false
                },
                {
                    "name": "service_category_id",
                    "type": "key",
                    "nullable": false,
                    "unique": false
                },
                {
                    "name": "price",
                    "type": "unsignedDouble",
                    "nullable": false,
                    "unique": false
                },
                {
                    "name": "status",
                    "type": "integer",
                    "nullable": false,
                    "unique": false
                },
                {
                    "name": "description",
                    "type": "translatable",
                    "nullable": true,
                    "unique": false
                },
                {
                    "name": "clinic_id",
                    "type": "key",
                    "nullable": false,
                    "unique": false
                }
            ],
            "relations": {
                "belongsTo": [
                    {
                        "type": "belongsTo",
                        "model_name": "ServiceCategory",
                        "key": "servicecategory_id"
                    },
                    {
                        "type": "belongsTo",
                        "model_name": "Clinic",
                        "key": "clinic_id"
                    }
                ]
            }
        },
        {
            "model_name": "Appointment",
            "table_name": "appointments",
            "attributes": [
                {
                    "name": "customer_id",
                    "type": "key",
                    "nullable": false,
                    "unique": false
                },
                {
                    "name": "clinic_id",
                    "type": "key",
                    "nullable": false,
                    "unique": false
                },
                {
                    "name": "note",
                    "type": "text",
                    "nullable": true,
                    "unique": false
                },
                {
                    "name": "service_id",
                    "type": "key",
                    "nullable": false,
                    "unique": false
                },
                {
                    "name": "extra_fees",
                    "type": "unsignedDouble",
                    "nullable": false,
                    "unique": false
                },
                {
                    "name": "total_cost",
                    "type": "unsignedDouble",
                    "nullable": false,
                    "unique": false
                },
                {
                    "name": "type",
                    "type": "string",
                    "nullable": false,
                    "unique": false
                },
                {
                    "name": "date",
                    "type": "date",
                    "nullable": false,
                    "unique": false
                },
                {
                    "name": "from",
                    "type": "time",
                    "nullable": false,
                    "unique": false
                },
                {
                    "name": "to",
                    "type": "time",
                    "nullable": false,
                    "unique": false
                },
                {
                    "name": "status",
                    "type": "string",
                    "nullable": false,
                    "unique": false
                },
                {
                    "name": "device_type",
                    "type": "string",
                    "nullable": true,
                    "unique": false
                },
                {
                    "name": "appointment_sequence",
                    "type": "bigInteger",
                    "nullable": false,
                    "unique": false
                },
                {
                    "name": "qr_code",
                    "type": "file",
                    "nullable": false,
                    "unique": false
                }
            ],
            "relations": {
                "belongsTo": [
                    {
                        "type": "belongsTo",
                        "model_name": "Customer",
                        "key": "customer_id"
                    },
                    {
                        "type": "belongsTo",
                        "model_name": "Clinic",
                        "key": "clinic_id"
                    },
                    {
                        "type": "belongsTo",
                        "model_name": "Service",
                        "key": "service_id"
                    }
                ],
                "hasMany": [
                    {
                        "type": "hasMany",
                        "model_name": "AppointmentLog"
                    }
                ]
            }
        },
        {
            "model_name": "AppointmentLog",
            "table_name": "appointment_logs",
            "attributes": [
                {
                    "name": "appointment_id",
                    "type": "key",
                    "nullable": true,
                    "unique": true
                },
                {
                    "name": "cancellation_reason",
                    "type": "text",
                    "nullable": false,
                    "unique": true
                },
                {
                    "name": "status",
                    "type": "string",
                    "nullable": true,
                    "unique": true
                },
                {
                    "name": "actor_id",
                    "type": "key",
                    "nullable": false,
                    "unique": true
                },
                {
                    "name": "affected_id",
                    "type": "key",
                    "nullable": false,
                    "unique": true
                },
                {
                    "name": "happen_in",
                    "type": "dateTime",
                    "nullable": true,
                    "unique": true
                }
            ],
            "relations": {
                "belongsTo": [
                    {
                        "type": "belongsTo",
                        "model_name": "Appointment",
                        "key": "appointment_id"
                    },
                    {
                        "type": "belongsTo",
                        "model_name": "Actor",
                        "key": "actor_id"
                    },
                    {
                        "type": "belongsTo",
                        "model_name": "Affected",
                        "key": "affected_id"
                    }
                ]
            }
        },
        {
            "model_name": "Medicine",
            "table_name": "medicines",
            "attributes": [
                {
                    "name": "name",
                    "type": "string",
                    "nullable": true,
                    "unique": true
                },
                {
                    "name": "description",
                    "type": "text",
                    "nullable": false,
                    "unique": true
                },
                {
                    "name": "clinic_id",
                    "type": "key",
                    "nullable": true,
                    "unique": true
                }
            ],
            "relations": {
                "belongsTo": [
                    {
                        "type": "belongsTo",
                        "model_name": "Clinic",
                        "key": "clinic_id"
                    }
                ],
                "manyToMany": [
                    {
                        "model_name": "Prescription",
                        "type": "manyToMany"
                    }
                ]
            }
        },
        {
            "model_name": "Prescription",
            "table_name": "prescriptions",
            "attributes": [
                {
                    "name": "clinic_id",
                    "type": "key",
                    "nullable": false,
                    "unique": false
                },
                {
                    "name": "customer_id",
                    "type": "key",
                    "nullable": false,
                    "unique": false
                },
                {
                    "name": "physical_information",
                    "type": "json",
                    "nullable": true,
                    "unique": false
                },
                {
                    "name": "problem_description",
                    "type": "text",
                    "nullable": true,
                    "unique": false
                },
                {
                    "name": "test",
                    "type": "text",
                    "nullable": true,
                    "unique": false
                },
                {
                    "name": "next_visit",
                    "type": "string",
                    "nullable": true,
                    "unique": false
                }
            ],
            "relations": {
                "belongsTo": [
                    {
                        "type": "belongsTo",
                        "model_name": "Clinic",
                        "key": "clinic_id"
                    },
                    {
                        "type": "belongsTo",
                        "model_name": "Customer",
                        "key": "customer_id"
                    }
                ],
                "manyToMany": [
                    {
                        "type": "manyToMany",
                        "model_name": "Medicine"
                    }
                ]
            }
        },
        {
            "model_name": "MedicinePrescription",
            "table_name": "medicine_prescriptions",
            "attributes": []
        },
        {
            "model_name": "BlockedItem",
            "table_name": "blocked_items",
            "attributes": [
                {
                    "name": "type",
                    "type": "string",
                    "nullable": true,
                    "unique": true
                },
                {
                    "name": "value",
                    "type": "string",
                    "nullable": true,
                    "unique": false
                }
            ],
            "relations": []
        },
        {
            "model_name": "Subscription",
            "table_name": "subscriptions",
            "attributes": [
                {
                    "name": "name",
                    "type": "string",
                    "nullable": false,
                    "unique": false
                },
                {
                    "name": "description",
                    "type": "text",
                    "nullable": true,
                    "unique": false
                },
                {
                    "name": "period",
                    "type": "integer",
                    "nullable": false,
                    "unique": false
                },
                {
                    "name": "allow_period",
                    "type": "integer",
                    "nullable": false,
                    "unique": false
                },
                {
                    "name": "deduction_cost",
                    "type": "float",
                    "nullable": false,
                    "unique": false
                }
            ],
            "relations": {
                "manyToMany": [
                    {
                        "type": "manyToMany",
                        "model_name": "Clinic"
                    }
                ]
            }
        },
        {
            "model_name": "Enquiry",
            "table_name": "enquiries",
            "attributes": [
                {
                    "name": "name",
                    "type": "string",
                    "nullable": false,
                    "unique": false
                },
                {
                    "name": "email",
                    "type": "string",
                    "nullable": false,
                    "unique": false
                },
                {
                    "name": "message",
                    "type": "text",
                    "nullable": false,
                    "unique": false
                },
                {
                    "name": "read_at",
                    "type": "dateTime",
                    "nullable": true,
                    "unique": false
                }
            ],
            "relations": []
        },
        {
            "model_name": "ClinicSubscription",
            "table_name": "clinic_subscriptions",
            "attributes": []
        },
        {
            "model_name": "Offer",
            "table_name": "offers",
            "attributes": [
                {
                    "name": "title",
                    "type": "translatable",
                    "nullable": false,
                    "unique": false
                },
                {
                    "name": "value",
                    "type": "float",
                    "nullable": false,
                    "unique": false
                },
                {
                    "name": "note",
                    "type": "translatable",
                    "nullable": true,
                    "unique": false
                },
                {
                    "name": "start_at",
                    "type": "date",
                    "nullable": false,
                    "unique": false
                },
                {
                    "name": "end_at",
                    "type": "date",
                    "nullable": false,
                    "unique": false
                },
                {
                    "name": "is_active",
                    "type": "boolean",
                    "nullable": false,
                    "unique": false
                },
                {
                    "name": "type",
                    "type": "string",
                    "nullable": false,
                    "unique": false
                },
                {
                    "name": "clinic_id",
                    "type": "key",
                    "nullable": false,
                    "unique": false
                }
            ],
            "relations": {
                "belongsTo": [
                    {
                        "type": "belongsTo",
                        "model_name": "Clinic",
                        "key": "clinic_id"
                    }
                ]
            }
        }
    ]
}